{
  "LessonsData": [
    {
      "Monday": {
      "lessonsData": {
        "up": ["ІЗВП (1 група)", "Фізичне виховання", "Основи охорони праці", "ІЗВП (2 група)", "Розробка веб (2 група)"],
        "down": ["ІЗВП (1 група)", "Фізичне виховання", "Основи охорони праці", "ІЗВП (2 група)", "Немає"]
        },
      "lessonsTime": {
        "1": { "begin": "9:00", "end": "10:20" },
        "2": { "begin": "10:30", "end": "11:50" },
        "3": { "begin": "12:20", "end": "13:40" },
        "4": { "begin": "13:50", "end": "15:10" },
        "5": { "begin": "15:20", "end": "16:40" }
        }  
      }
    },
    {
      "Thuesday": {
      "lessonsData": {
        "up": ['ІЗВП', 'Програмування для мобільних пристроїв', 'Основи охорони праці', 'Класна година', 'Немає'],
        "down": ['ТП мовою Java', 'Програмування для мобільних пристроїв', 'ОПІ', 'Класна година', 'Немає']
      },
      "lessonsTime": {
        "1": { "begin": "9:00", "end": "10:20" },
        "2": { "begin": "10:30", "end": "11:50" },
        "3": { "begin": "12:20", "end": "13:40" },
        "4": { "begin": "13:50", "end": "15:10" },
        "5": { "begin": "15:20", "end": "16:40" }
      }
    }
    },
    {
      "Wednesday": {
      "lessonsData": {
        "up": ['Розробка веб (1 група)', 'Основи охорони праці', 'ОПІ', 'Фізичне виховання', 'Немає'],
        "down": ['Розробка КСА (2 група)', 'Основи охорони праці', 'Розробка КСА (1 група)', 'Фізичне виховання', 'Програмування для мобільних пристроїв']
      },
      "lessonsTime": {
        "1": { "begin": "9:00", "end": "10:20" },
        "2": { "begin": "10:30", "end": "11:50" },
        "3": { "begin": "12:20", "end": "13:40" },
        "4": { "begin": "13:50", "end": "15:10" },
        "5": { "begin": "15:20", "end": "16:40" }
      }
    }
    },
    {
      "Thursday": {
      "lessonsData": {
        "up": ['Розробка КСА (1 група)', 'ТП мовою Java (1 група)', 'ОПІ', 'Розробка КСА (2 група)', 'ТП мовою Java (2 група)'],
        "down": ['Розробка КСА (1 група)', 'ТП мовою Java (1 група)', 'Розробка веб (1 група)', 'Розробка КСА (2 група)', 'ТП мовою Java (2 група)']
      },
      "lessonsTime": {
        "1": { "begin": "9:00", "end": "10:20" },
        "2": { "begin": "10:30", "end": "11:50" },
        "3": { "begin": "12:20", "end": "13:40" },
        "4": { "begin": "13:50", "end": "15:10" },
        "5": { "begin": "15:20", "end": "16:40" }
      }
    }
    },
     {
      "Friday": {
      "lessonsData": {
        "up": ['Програмування для МП (1 група)', 'ІЗВП', 'Розробка КСА', 'Програмування для МП (2 група)', 'Немає'],
        "down": ['Програмування для МП (1 група)', 'ІЗВП', 'Розробка КСА', 'Програмування для МП (2 група)', 'Немає']
      },
      "lessonsTime": {
        "1": { "begin": "9:00", "end": "10:20" },
        "2": { "begin": "10:30", "end": "11:50" },
        "3": { "begin": "12:20", "end": "13:40" },
        "4": { "begin": "13:50", "end": "15:10" },
        "5": { "begin": "15:20", "end": "16:40" }
      }
    }
    }
  ]
}
